pgfgen/__init__.py
pgfgen/__main__.py
pgfgen/config.py
pgfgen/defaults.py
pgfgen/exceptions.py
pgfgen/py.typed
pgfgen/templating.py
pgfgen/types.py
pgfgen/util.py
pgfgen/svg/__init__.py
pgfgen/svg/generator.py
pgfgen/svg/nodes.py
pgfgen/svg/visitor.py
pgfgen-0.6.2.dist-info/LICENSE.txt
pgfgen-0.6.2.dist-info/METADATA
pgfgen-0.6.2.dist-info/WHEEL
pgfgen-0.6.2.dist-info/entry_points.txt
pgfgen-0.6.2.dist-info/top_level.txt
pgfgen-0.6.2.dist-info/RECORD
