Metadata-Version: 2.1
Name: pgfgen
Version: 0.6.2
Summary: Template-based PGF generator
Author-email: Paweł Tomulik <ptomulik@wp.pl>
License: Copyright 2022 Paweł Tomulik <ptomulik@wp.pl>
Project-URL: homepage, https://github.com/ptomulik/pgfgen
Project-URL: repository, https://github.com/ptomulik/pgfgen
Keywords: svg,pgf,converter,templates,jinja
Classifier: Development Status :: 2 - Pre-Alpha
Classifier: Intended Audience :: Developers
Classifier: License :: OSI Approved :: MIT License
Classifier: Operating System :: OS Independent
Classifier: Programming Language :: Python
Classifier: Programming Language :: Python :: 3.9
Classifier: Programming Language :: Python :: 3.10
Classifier: Programming Language :: Python :: Implementation :: PyPy
Classifier: Topic :: Multimedia :: Graphics
Classifier: Topic :: Multimedia :: Graphics :: Editors :: Vector-Based
Classifier: Topic :: Software Development :: Libraries :: Python Modules
Classifier: Topic :: Utilities
Requires-Python: >=3.9
License-File: LICENSE.txt
Requires-Dist: svgelements (>=1.8.3)
Requires-Dist: jinja2 (>=3.1.2)
Requires-Dist: tomli (>=2.0.1)
Requires-Dist: typing-extensions (>=4.3.0)
Provides-Extra: dev
Requires-Dist: mypy (>=0.971) ; extra == 'dev'
Requires-Dist: pyproject-flake8 (>=5.0.3) ; extra == 'dev'
Requires-Dist: coverage (>=6.5.0) ; extra == 'dev'
Requires-Dist: pylint (>=2.15.3) ; extra == 'dev'
Requires-Dist: black (>=22.8.0) ; extra == 'dev'
Requires-Dist: bumpver (>=2022.1118) ; extra == 'dev'
Requires-Dist: build (>=0.8.0) ; extra == 'dev'
Requires-Dist: twine (>=4.0.1) ; extra == 'dev'
